<?xml version="1.0" encoding="utf-8"?>
<-- todo: So, which entity is really working, this one, or Battery in Entity folder? you should remove one of entities definitions -->
<doctrine-mapping xmlns="http://doctrine-project.org/schemas/orm/doctrine-mapping" xmlns:xsi="http://www.w3.org/2001/XMLSchema-instance" xsi:schemaLocation="http://doctrine-project.org/schemas/orm/doctrine-mapping http://doctrine-project.org/schemas/orm/doctrine-mapping.xsd">
  <entity name="Training\Bundle\BatteryBundle\Entity\Battery" table="battery">
    <id name="id" type="integer" column="id">
      <generator strategy="IDENTITY"/>
    </id>
    <field name="type" type="string" column="type" length="255" nullable="false"/>
    <field name="count" type="integer" column="count" nullable="false"/>
    <field name="name" type="string" column="name" length="255" nullable="false"/>
  </entity>
</doctrine-mapping>
